Metadata-Version: 1.0
Name: thom023
Version: 0.23
Summary: Gaussian distributions
Home-page: UNKNOWN
Author: Nguyen Huong Thom
Author-email: rajatsharma369007@gmail.com
License: UNKNOWN
Platform: UNKNOWN
